raw/__init__.py
raw/db.py
sqla_raw-1.7.0.dist-info/LICENSE.txt
sqla_raw-1.7.0.dist-info/METADATA
sqla_raw-1.7.0.dist-info/WHEEL
sqla_raw-1.7.0.dist-info/top_level.txt
sqla_raw-1.7.0.dist-info/RECORD
