Metadata-Version: 2.2
Name: sqla-raw
Version: 1.7.0
Summary: A tiny library for submitting raw SQL via SQLAlchemy
Home-page: https://github.com/nerium-data/sqla-raw
Author: Thomas Yager-Madden
Author-email: thomas@yager-madden.com
Classifier: Development Status :: 5 - Production/Stable
Classifier: Environment :: Console
Classifier: Environment :: Web Environment
Classifier: License :: OSI Approved :: MIT License
Classifier: Operating System :: OS Independent
Classifier: Programming Language :: Python
Classifier: Programming Language :: Python :: 3
Classifier: Programming Language :: Python :: 3.6
Classifier: Programming Language :: Python :: 3.7
Classifier: Programming Language :: Python :: 3.8
Classifier: Programming Language :: Python :: 3.9
Classifier: Programming Language :: Python :: 3.10
Classifier: Programming Language :: Python :: 3.11
Classifier: Topic :: Database :: Front-Ends
Classifier: Topic :: Software Development :: Libraries
Classifier: Topic :: Utilities
Requires-Python: >=3.7.0
License-File: LICENSE.txt
Requires-Dist: cryptography
Requires-Dist: jinja2
Requires-Dist: sqlalchemy
Provides-Extra: mysql
Requires-Dist: PyMySQL; extra == "mysql"
Provides-Extra: pg
Requires-Dist: psycopg; extra == "pg"
Dynamic: author
Dynamic: author-email
Dynamic: classifier
Dynamic: description
Dynamic: description-content-type
Dynamic: home-page
Dynamic: provides-extra
Dynamic: requires-dist
Dynamic: requires-python
Dynamic: summary
